LICENSE
MANIFEST.in
README.rst
THIRD-PARTY-NOTICES
ez_setup.py
setup.py
bson/__init__.py
bson/_cbsonmodule.c
bson/_cbsonmodule.h
bson/binary.py
bson/bson-endian.h
bson/bson-stdint-win32.h
bson/buffer.c
bson/buffer.h
bson/code.py
bson/codec_options.py
bson/dbref.py
bson/decimal128.py
bson/encoding_helpers.c
bson/encoding_helpers.h
bson/errors.py
bson/int64.py
bson/json_util.py
bson/max_key.py
bson/min_key.py
bson/objectid.py
bson/py3compat.py
bson/raw_bson.py
bson/regex.py
bson/son.py
bson/time64.c
bson/time64.h
bson/time64_config.h
bson/time64_limits.h
bson/timestamp.py
bson/tz_util.py
doc/__init__.py
doc/atlas.rst
doc/changelog.rst
doc/compatibility-policy.rst
doc/conf.py
doc/contributors.rst
doc/faq.rst
doc/index.rst
doc/installation.rst
doc/migrate-to-pymongo3.rst
doc/mongo_extensions.py
doc/python3.rst
doc/tools.rst
doc/tutorial.rst
doc/api/index.rst
doc/api/bson/binary.rst
doc/api/bson/code.rst
doc/api/bson/codec_options.rst
doc/api/bson/dbref.rst
doc/api/bson/decimal128.rst
doc/api/bson/errors.rst
doc/api/bson/index.rst
doc/api/bson/int64.rst
doc/api/bson/json_util.rst
doc/api/bson/max_key.rst
doc/api/bson/min_key.rst
doc/api/bson/objectid.rst
doc/api/bson/raw_bson.rst
doc/api/bson/regex.rst
doc/api/bson/son.rst
doc/api/bson/timestamp.rst
doc/api/bson/tz_util.rst
doc/api/gridfs/errors.rst
doc/api/gridfs/grid_file.rst
doc/api/gridfs/index.rst
doc/api/pymongo/bulk.rst
doc/api/pymongo/change_stream.rst
doc/api/pymongo/client_session.rst
doc/api/pymongo/collation.rst
doc/api/pymongo/collection.rst
doc/api/pymongo/command_cursor.rst
doc/api/pymongo/cursor.rst
doc/api/pymongo/cursor_manager.rst
doc/api/pymongo/database.rst
doc/api/pymongo/errors.rst
doc/api/pymongo/index.rst
doc/api/pymongo/ismaster.rst
doc/api/pymongo/message.rst
doc/api/pymongo/mongo_client.rst
doc/api/pymongo/mongo_replica_set_client.rst
doc/api/pymongo/monitoring.rst
doc/api/pymongo/operations.rst
doc/api/pymongo/pool.rst
doc/api/pymongo/read_concern.rst
doc/api/pymongo/read_preferences.rst
pymongo_amplidata.egg-info/PKG-INFO
pymongo_amplidata.egg-info/SOURCES.txt
pymongo_amplidata.egg-info/dependency_links.txt
pymongo_amplidata.egg-info/pbr.json
pymongo_amplidata.egg-info/requires.txt
pymongo_amplidata.egg-info/top_level.txt
