Metadata-Version: 1.1
Name: pymongo-amplidata
Version: 3.6.0.post1
Summary: Python driver for MongoDB <http://www.mongodb.org>
Home-page: https://github.com/amplidata/mongo-python-driver
Author: Bret Curtis
Author-email: bret.curtis@wdc.com
License: Apache License, Version 2.0
Keywords: mongo,mongodb,pymongo,gridfs,bson
Platform: UNKNOWN
Classifier: Development Status :: 5 - Production/Stable
Classifier: Intended Audience :: Developers
Classifier: License :: OSI Approved :: Apache Software License
Classifier: Operating System :: MacOS :: MacOS X
Classifier: Operating System :: Microsoft :: Windows
Classifier: Operating System :: POSIX
Classifier: Programming Language :: Python :: 2
Classifier: Programming Language :: Python :: 2.6
Classifier: Programming Language :: Python :: 2.7
Classifier: Programming Language :: Python :: 3
Classifier: Programming Language :: Python :: 3.4
Classifier: Programming Language :: Python :: 3.5
Classifier: Programming Language :: Python :: 3.6
Classifier: Programming Language :: Python :: Implementation :: CPython
Classifier: Programming Language :: Python :: Implementation :: PyPy
Classifier: Topic :: Database
